{"generatedAt":1734264649860,"generateTime":407,"contents":[{"_path":"/","_dir":"","_draft":false,"_partial":false,"_locale":"","title":"About","description":"Stepan Vinokurov's Portfolio","layout":"default","head":{"title":"Stepan Vinokurov"},"body":{"type":"root","children":[{"type":"element","tag":"hero","props":{"image":"/hero_image.jpeg"},"children":[{"type":"element","tag":"template","props":{"v-slot:title":""},"children":[{"type":"element","tag":"p","props":{},"children":[{"type":"text","value":"Hi, ステパンです."}]}]},{"type":"element","tag":"template","props":{"v-slot:description":""},"children":[{"type":"element","tag":"pre","props":{"className":"language-json shiki shiki-themes github-light github-dark","code":"{\n    name: Stepan,\n    age: 28,\n    position: Full-Stack Web Engineer,\n    experience: 2年間以上\n}\n","language":"json","meta":"","style":""},"children":[{"type":"element","tag":"code","props":{"__ignoreMap":""},"children":[{"type":"element","tag":"span","props":{"class":"line","line":1},"children":[{"type":"element","tag":"span","props":{"style":"--shiki-default:#24292E;--shiki-dark:#E1E4E8"},"children":[{"type":"text","value":"{\n"}]}]},{"type":"element","tag":"span","props":{"class":"line","line":2},"children":[{"type":"element","tag":"span","props":{"style":"--shiki-default:#B31D28;--shiki-default-font-style:italic;--shiki-dark:#FDAEB7;--shiki-dark-font-style:italic"},"children":[{"type":"text","value":"    name"}]},{"type":"element","tag":"span","props":{"style":"--shiki-default:#24292E;--shiki-dark:#E1E4E8"},"children":[{"type":"text","value":": "}]},{"type":"element","tag":"span","props":{"style":"--shiki-default:#B31D28;--shiki-default-font-style:italic;--shiki-dark:#FDAEB7;--shiki-dark-font-style:italic"},"children":[{"type":"text","value":"Stepan"}]},{"type":"element","tag":"span","props":{"style":"--shiki-default:#24292E;--shiki-dark:#E1E4E8"},"children":[{"type":"text","value":",\n"}]}]},{"type":"element","tag":"span","props":{"class":"line","line":3},"children":[{"type":"element","tag":"span","props":{"style":"--shiki-default:#B31D28;--shiki-default-font-style:italic;--shiki-dark:#FDAEB7;--shiki-dark-font-style:italic"},"children":[{"type":"text","value":"    age"}]},{"type":"element","tag":"span","props":{"style":"--shiki-default:#24292E;--shiki-dark:#E1E4E8"},"children":[{"type":"text","value":": "}]},{"type":"element","tag":"span","props":{"style":"--shiki-default:#005CC5;--shiki-dark:#79B8FF"},"children":[{"type":"text","value":"28"}]},{"type":"element","tag":"span","props":{"style":"--shiki-default:#24292E;--shiki-dark:#E1E4E8"},"children":[{"type":"text","value":",\n"}]}]},{"type":"element","tag":"span","props":{"class":"line","line":4},"children":[{"type":"element","tag":"span","props":{"style":"--shiki-default:#B31D28;--shiki-default-font-style:italic;--shiki-dark:#FDAEB7;--shiki-dark-font-style:italic"},"children":[{"type":"text","value":"    position"}]},{"type":"element","tag":"span","props":{"style":"--shiki-default:#24292E;--shiki-dark:#E1E4E8"},"children":[{"type":"text","value":": "}]},{"type":"element","tag":"span","props":{"style":"--shiki-default:#B31D28;--shiki-default-font-style:italic;--shiki-dark:#FDAEB7;--shiki-dark-font-style:italic"},"children":[{"type":"text","value":"Full-Stack"}]},{"type":"element","tag":"span","props":{"style":"--shiki-default:#B31D28;--shiki-default-font-style:italic;--shiki-dark:#FDAEB7;--shiki-dark-font-style:italic"},"children":[{"type":"text","value":" Web"}]},{"type":"element","tag":"span","props":{"style":"--shiki-default:#B31D28;--shiki-default-font-style:italic;--shiki-dark:#FDAEB7;--shiki-dark-font-style:italic"},"children":[{"type":"text","value":" Engineer"}]},{"type":"element","tag":"span","props":{"style":"--shiki-default:#24292E;--shiki-dark:#E1E4E8"},"children":[{"type":"text","value":",\n"}]}]},{"type":"element","tag":"span","props":{"class":"line","line":5},"children":[{"type":"element","tag":"span","props":{"style":"--shiki-default:#B31D28;--shiki-default-font-style:italic;--shiki-dark:#FDAEB7;--shiki-dark-font-style:italic"},"children":[{"type":"text","value":"    experience"}]},{"type":"element","tag":"span","props":{"style":"--shiki-default:#24292E;--shiki-dark:#E1E4E8"},"children":[{"type":"text","value":": "}]},{"type":"element","tag":"span","props":{"style":"--shiki-default:#005CC5;--shiki-dark:#79B8FF"},"children":[{"type":"text","value":"2"}]},{"type":"element","tag":"span","props":{"style":"--shiki-default:#B31D28;--shiki-default-font-style:italic;--shiki-dark:#FDAEB7;--shiki-dark-font-style:italic"},"children":[{"type":"text","value":"年間以上\n"}]}]},{"type":"element","tag":"span","props":{"class":"line","line":6},"children":[{"type":"element","tag":"span","props":{"style":"--shiki-default:#24292E;--shiki-dark:#E1E4E8"},"children":[{"type":"text","value":"}\n"}]}]}]}]}]}]},{"type":"element","tag":"p","props":{},"children":[{"type":"text","value":"以前はホスピタリティ業界で働いていましたが、自分自身が成長していないことに気づき、より挑戦的でやりがいのある仕事を求めてキャリアを変えることにしました。"}]},{"type":"element","tag":"p","props":{},"children":[{"type":"text","value":"現在はWebエンジニアとして働いています。私の仕事は、直接顧客とやり取りし、彼らの問題に対する解決策を設計し、実装することです。"}]},{"type":"element","tag":"p","props":{},"children":[{"type":"text","value":"常に新しいことを学び、Web開発の知識を広げることを心がけています。複雑な問題を解決することが好きです。"}]},{"type":"element","tag":"p","props":{},"children":[{"type":"text","value":"柔軟性、ビジネスの観点からの考え、多種多様な問題を解決する能力を提供します。"}]},{"type":"element","tag":"h3","props":{"id":"スキル"},"children":[{"type":"text","value":"スキル"}]},{"type":"element","tag":"ul","props":{},"children":[{"type":"element","tag":"li","props":{},"children":[{"type":"text","value":"フロントエンド: HTML, CSS (Tailwind, Bootstrap, Vuetify), JavaScript (Vue 3/Nuxt 3), WordPress"}]},{"type":"element","tag":"li","props":{},"children":[{"type":"text","value":"バックエンド: Python, php (Laravel)"}]},{"type":"element","tag":"li","props":{},"children":[{"type":"text","value":"他: Firebase, mySQL, Git, Docker, Linux"}]}]},{"type":"element","tag":"h3","props":{"id":"学歴と職歴"},"children":[{"type":"text","value":"学歴と職歴"}]},{"type":"element","tag":"ul","props":{},"children":[{"type":"element","tag":"li","props":{},"children":[{"type":"text","value":"株式会社 WitOne (2023年10月~)"}]},{"type":"element","tag":"li","props":{},"children":[{"type":"text","value":"株式会社 Opus (2021年10月 - 2023年9月)"}]},{"type":"element","tag":"li","props":{},"children":[{"type":"text","value":"株式会社 KPG HOTEL & RESORT (2020年4月 - 2021年4月)"}]},{"type":"element","tag":"li","props":{},"children":[{"type":"text","value":"UNITAS 日本語学校 (2018年4月 - 2020年3月)"}]},{"type":"element","tag":"li","props":{},"children":[{"type":"text","value":"North-Eastern Federal University (2013年9月 - 2017年5月)"}]}]},{"type":"element","tag":"h3","props":{"id":"言語"},"children":[{"type":"text","value":"言語"}]},{"type":"element","tag":"ul","props":{},"children":[{"type":"element","tag":"li","props":{},"children":[{"type":"text","value":"日本語 (JLPT N2)"}]},{"type":"element","tag":"li","props":{},"children":[{"type":"text","value":"英語 (ビジネスレベル)"}]},{"type":"element","tag":"li","props":{},"children":[{"type":"text","value":"ロシア語 (母国語)"}]},{"type":"element","tag":"li","props":{},"children":[{"type":"text","value":"サハ語 (母語)"}]}]},{"type":"element","tag":"style","props":{},"children":[{"type":"text","value":"html .default .shiki span {color: var(--shiki-default);background: var(--shiki-default-bg);font-style: var(--shiki-default-font-style);font-weight: var(--shiki-default-font-weight);text-decoration: var(--shiki-default-text-decoration);}html .shiki span {color: var(--shiki-default);background: var(--shiki-default-bg);font-style: var(--shiki-default-font-style);font-weight: var(--shiki-default-font-weight);text-decoration: var(--shiki-default-text-decoration);}html .dark .shiki span {color: var(--shiki-dark);background: var(--shiki-dark-bg);font-style: var(--shiki-dark-font-style);font-weight: var(--shiki-dark-font-weight);text-decoration: var(--shiki-dark-text-decoration);}html.dark .shiki span {color: var(--shiki-dark);background: var(--shiki-dark-bg);font-style: var(--shiki-dark-font-style);font-weight: var(--shiki-dark-font-weight);text-decoration: var(--shiki-dark-text-decoration);}"}]}],"toc":{"title":"","searchDepth":2,"depth":2,"links":[{"id":"スキル","depth":3,"text":"スキル"},{"id":"学歴と職歴","depth":3,"text":"学歴と職歴"},{"id":"言語","depth":3,"text":"言語"}]}},"_type":"markdown","_id":"content:1.index.md","_source":"content","_file":"1.index.md","_stem":"1.index","_extension":"md"},{"_path":"/articles","_dir":"","_draft":false,"_partial":false,"_locale":"","title":"Projects","description":"","layout":"page","body":{"type":"root","children":[{"type":"element","tag":"h3","props":{"id":"参加したプロジェクト"},"children":[{"type":"text","value":"参加したプロジェクト"}]},{"type":"element","tag":"table","props":{},"children":[{"type":"element","tag":"thead","props":{},"children":[{"type":"element","tag":"tr","props":{},"children":[{"type":"element","tag":"th","props":{},"children":[{"type":"text","value":"期間"}]},{"type":"element","tag":"th","props":{},"children":[{"type":"text","value":"担当"}]},{"type":"element","tag":"th","props":{},"children":[{"type":"text","value":"ツール"}]},{"type":"element","tag":"th","props":{},"children":[{"type":"text","value":"業務内容"}]}]}]},{"type":"element","tag":"tbody","props":{},"children":[{"type":"element","tag":"tr","props":{},"children":[{"type":"element","tag":"td","props":{},"children":[{"type":"text","value":"2023.06 ~ 2023.12"}]},{"type":"element","tag":"td","props":{},"children":[{"type":"text","value":"Web エンジニア"}]},{"type":"element","tag":"td","props":{},"children":[{"type":"text","value":"Vue 3/Nuxt 3/Firebase"}]},{"type":"element","tag":"td","props":{},"children":[{"type":"element","tag":"strong","props":{},"children":[{"type":"text","value":"データ収集ツール・さまざまな SNS からユーザーの印象をまとめる SaaS アプリ"}]},{"type":"element","tag":"br","props":{},"children":[]},{"type":"text","value":" - チームリード "},{"type":"element","tag":"br","props":{},"children":[]},{"type":"text","value":" - 設計 "},{"type":"element","tag":"br","props":{},"children":[]},{"type":"text","value":" - 完全な開発"}]}]},{"type":"element","tag":"tr","props":{},"children":[{"type":"element","tag":"td","props":{},"children":[{"type":"text","value":"2022.10 ~ 2023.06"}]},{"type":"element","tag":"td","props":{},"children":[{"type":"text","value":"Web エンジニア"}]},{"type":"element","tag":"td","props":{},"children":[{"type":"text","value":"php/Laravel/Ruby/MySQL/Docker/nginx/Twitter API"}]},{"type":"element","tag":"td","props":{},"children":[{"type":"element","tag":"strong","props":{},"children":[{"type":"text","value":"データ収集ツール・Twitter からユーザーの印象をまとめるアプリ"}]},{"type":"text","value":" "},{"type":"element","tag":"br","props":{},"children":[]},{"type":"text","value":" - 詳細設計 "},{"type":"element","tag":"br","props":{},"children":[]},{"type":"text","value":" - 機能の追加 "},{"type":"element","tag":"br","props":{},"children":[]},{"type":"text","value":" - リファクタリング"}]}]},{"type":"element","tag":"tr","props":{},"children":[{"type":"element","tag":"td","props":{},"children":[{"type":"text","value":"2022.06 ~ 2022.09"}]},{"type":"element","tag":"td","props":{},"children":[{"type":"text","value":"エンジニア"}]},{"type":"element","tag":"td","props":{},"children":[{"type":"text","value":"Python/PyQt"}]},{"type":"element","tag":"td","props":{},"children":[{"type":"element","tag":"strong","props":{},"children":[{"type":"text","value":"自動テストツール・デスクトップアプリ"}]},{"type":"text","value":" "},{"type":"element","tag":"br","props":{},"children":[]},{"type":"text","value":" - Mac 版のビルド作成 "},{"type":"element","tag":"br","props":{},"children":[]},{"type":"text","value":" - 新機能の実装 "},{"type":"element","tag":"br","props":{},"children":[]},{"type":"text","value":" - バグ修正"}]}]},{"type":"element","tag":"tr","props":{},"children":[{"type":"element","tag":"td","props":{},"children":[{"type":"text","value":"2022.01 ~ 2022.06"}]},{"type":"element","tag":"td","props":{},"children":[{"type":"text","value":"Web エンジニア"}]},{"type":"element","tag":"td","props":{},"children":[{"type":"text","value":"Vue 2/Python/WordPress/MySQL/Firebase/Docker"}]},{"type":"element","tag":"td","props":{},"children":[{"type":"element","tag":"strong","props":{},"children":[{"type":"text","value":"いくつかのプロダクトのランディングページの開発・アプリ管理画面"}]},{"type":"text","value":" "},{"type":"element","tag":"br","props":{},"children":[]},{"type":"text","value":" - 基本設計 "},{"type":"element","tag":"br","props":{},"children":[]},{"type":"text","value":" - UI デザイン "},{"type":"element","tag":"br","props":{},"children":[]},{"type":"text","value":" - マークアップ "},{"type":"element","tag":"br","props":{},"children":[]},{"type":"text","value":" - サーバー側の機能の開発/Web API の作成 "},{"type":"element","tag":"br","props":{},"children":[]},{"type":"text","value":" - アプリ管理画面 "},{"type":"element","tag":"br","props":{},"children":[]},{"type":"text","value":" - SEO"}]}]},{"type":"element","tag":"tr","props":{},"children":[{"type":"element","tag":"td","props":{},"children":[{"type":"text","value":"2021.10 ~ 2021.12"}]},{"type":"element","tag":"td","props":{},"children":[{"type":"text","value":"フロントエンド"}]},{"type":"element","tag":"td","props":{},"children":[{"type":"text","value":"Vue 2/Nuxt 2/Firebase"}]},{"type":"element","tag":"td","props":{},"children":[{"type":"element","tag":"strong","props":{},"children":[{"type":"text","value":"動画修正指示プロジェクトの開発・チームでビデオ編集に取り組むプロジェクト"}]},{"type":"element","tag":"br","props":{},"children":[]},{"type":"text","value":" - 追加機能 "},{"type":"element","tag":"br","props":{},"children":[]},{"type":"text","value":" - PDF ビューアの作成 "},{"type":"element","tag":"br","props":{},"children":[]},{"type":"text","value":" - コンポーネントの作成 "},{"type":"element","tag":"br","props":{},"children":[]},{"type":"text","value":" - バグ修正 "},{"type":"element","tag":"br","props":{},"children":[]},{"type":"text","value":" - i18n・国際化の翻訳と実装"}]}]}]}]},{"type":"element","tag":"h3","props":{"id":"ゼロから作ったプロジェクト"},"children":[{"type":"text","value":"ゼロから作ったプロジェクト"}]},{"type":"element","tag":"articles-list","props":{},"children":[{"type":"element","tag":"hr","props":{},"children":[]},{"type":"element","tag":"p","props":{},"children":[{"type":"text","value":"path: articles"}]},{"type":"element","tag":"hr","props":{},"children":[]}]}],"toc":{"title":"","searchDepth":2,"depth":2,"links":[{"id":"参加したプロジェクト","depth":3,"text":"参加したプロジェクト"},{"id":"ゼロから作ったプロジェクト","depth":3,"text":"ゼロから作ったプロジェクト"}]}},"_type":"markdown","_id":"content:2.articles.md","_source":"content","_file":"2.articles.md","_stem":"2.articles","_extension":"md"},{"_path":"/contact","_dir":"","_draft":false,"_partial":false,"_locale":"","title":"Contact","description":"","layout":"default","body":{"type":"root","children":[{"type":"element","tag":"h1","props":{"id":"get-in-touch"},"children":[{"type":"text","value":"Get in touch"}]},{"type":"element","tag":"contact-form","props":{":fields":"[{\"type\":\"text\",\"name\":\"name\",\"label\":\"Your name\",\"required\":true},{\"type\":\"email\",\"name\":\"email\",\"label\":\"Your email\",\"required\":true},{\"type\":\"text\",\"name\":\"subject\",\"label\":\"Subject\",\"required\":false},{\"type\":\"textarea\",\"name\":\"message\",\"label\":\"Message\",\"required\":true}]"},"children":[]}],"toc":{"title":"","searchDepth":2,"depth":2,"links":[]}},"_type":"markdown","_id":"content:3.contact.md","_source":"content","_file":"3.contact.md","_stem":"3.contact","_extension":"md"},{"_path":"/articles/oreo-2","_dir":"articles","_draft":false,"_partial":false,"_locale":"","title":"Oreo 2.0","description":"データ収集ツール・さまざまなSNSからユーザーの印象をまとめるSaaSアプリ","cover":"/articles/oreo2_1.png","date":"2023-08","layout":"article","body":{"type":"root","children":[{"type":"element","tag":"h1","props":{"id":"oreo-20"},"children":[{"type":"text","value":"Oreo 2.0"}]},{"type":"element","tag":"p","props":{},"children":[{"type":"text","value":"データ収集ツール・さまざまなSNSからユーザーの印象をまとめるSaaSアプリ。"}]},{"type":"element","tag":"img","props":{"src":"/articles/oreo2_1.png","width":"100%","height":"50%"},"children":[]},{"type":"element","tag":"p","props":{},"children":[{"type":"text","value":"TwitterやSteamからのユーザーの反応を集約するために設計されたツールです。 このプラットフォームは、AI を使用した高度な自然言語処理と画像認識を採用しており、ユーザーの感情に対する包括的な洞察を提供します。 このアプリは詳細なレポート ダッシュボードをシームレスに生成し、情報に基づいた意思決定のための貴重な情報を提供します。"}]},{"type":"element","tag":"img","props":{"src":"/articles/oreo2_2.png","width":"100%","height":"50%"},"children":[]},{"type":"element","tag":"p","props":{},"children":[{"type":"text","value":"技術スタック:"}]},{"type":"element","tag":"p","props":{},"children":[{"type":"text","value":"フロントエンド: Nuxt 3, TypeScript"}]},{"type":"element","tag":"p","props":{},"children":[{"type":"text","value":"スタイル: Tailwind CSS"}]},{"type":"element","tag":"p","props":{},"children":[{"type":"text","value":"バックエンド: Python, Cloud Functions, Firebase Firestore"}]},{"type":"element","tag":"p","props":{},"children":[{"type":"text","value":"API統合: Twitter API, Steam API"}]}],"toc":{"title":"","searchDepth":2,"depth":2,"links":[]}},"_type":"markdown","_id":"content:articles:1.oreo-2.md","_source":"content","_file":"articles/1.oreo-2.md","_stem":"articles/1.oreo-2","_extension":"md"}],"navigation":[{"title":"About","_path":"/","layout":"default"},{"title":"Projects","_path":"/articles","children":[{"title":"Oreo 2.0","_path":"/articles/oreo-2","layout":"article"}],"layout":"page"},{"title":"Contact","_path":"/contact","layout":"default"}]}